{
  "generated_at": "2026-02-26T10:17:04.196Z",
  "mining_depth": "comprehensive",
  "lookback_days": 90,
  "summary_metrics": {
    "issues_analyzed": 531,
    "commits_analyzed": 370,
    "prs_analyzed": 143,
    "technical_depth_score": 97,
    "collaboration_score": 60
  },
  "data_sources": {
    "issues_intelligence": true,
    "commits_intelligence": true,
    "prs_intelligence": true,
    "collaboration_patterns": true,
    "technical_expertise": true,
    "professional_narratives": true
  }
}